rushevent/__init__.py
rushevent-0.1.3.dist-info/licenses/LICENSE.txt
scripts/build.py
scripts/install.py
rushevent-0.1.3.dist-info/METADATA
rushevent-0.1.3.dist-info/WHEEL
rushevent-0.1.3.dist-info/top_level.txt
rushevent-0.1.3.dist-info/RECORD
