Metadata-Version: 2.4
Name: rushevent
Version: 0.1.3
Summary: python event
Author-email: ndrzy <dandan0019@outlook.com>
License: MIT
Project-URL: Homepage, https://github.com/meatdumplings0019/rushevent
Requires-Python: >=3.10
License-File: LICENSE.txt
Requires-Dist: pygame-ce
Dynamic: license-file
